LICENSE
README.md
setup.py
tests/__init__.py
tests/test_other_utils.py
tpu_util/__init__.py
tpu_util/_lr_finder.py
tpu_util/colab.py
tpu_util/kaggle.py
tpu_util/other_utils.py
tpu_util/tpu_cache_ds_utils.py
tpu_util/tpu_utility_1.py
tpu_util.egg-info/PKG-INFO
tpu_util.egg-info/SOURCES.txt
tpu_util.egg-info/dependency_links.txt
tpu_util.egg-info/requires.txt
tpu_util.egg-info/top_level.txt