Metadata-Version: 2.1
Name: tpu-util
Version: 0.1.3
Summary: TPU utility with PyTorch XLA
Home-page: https://github.com/Wabinab/TPU_utility
License: UNKNOWN
Platform: UNKNOWN
Requires-Python: >=3.6
License-File: LICENSE
